[
    {
        "key": "group_68b847e93c1e6",
        "title": "Compétences techniques",
        "fields": [
            {
                "key": "field_68b847e9083ff",
                "label": "Catégories de compétences",
                "name": "skills_categories",
                "aria-label": "",
                "type": "repeater",
                "instructions": "",
                "required": 0,
                "conditional_logic": 0,
                "wrapper": {
                    "width": "",
                    "class": "",
                    "id": ""
                },
                "layout": "table",
                "pagination": 0,
                "min": 0,
                "max": 0,
                "collapsed": "",
                "button_label": "Ajouter un élément",
                "rows_per_page": 20,
                "sub_fields": [
                    {
                        "key": "field_68b84b8040c1e",
                        "label": "Titre de la catégorie",
                        "name": "title",
                        "aria-label": "",
                        "type": "text",
                        "instructions": "",
                        "required": 0,
                        "conditional_logic": 0,
                        "wrapper": {
                            "width": "",
                            "class": "",
                            "id": ""
                        },
                        "default_value": "",
                        "maxlength": "",
                        "allow_in_bindings": 0,
                        "placeholder": "",
                        "prepend": "",
                        "append": "",
                        "parent_repeater": "field_68b847e9083ff"
                    },
                    {
                        "key": "field_68b84bcc40c1f",
                        "label": "Compétences",
                        "name": "competences",
                        "aria-label": "",
                        "type": "repeater",
                        "instructions": "",
                        "required": 0,
                        "conditional_logic": 0,
                        "wrapper": {
                            "width": "",
                            "class": "",
                            "id": ""
                        },
                        "layout": "table",
                        "pagination": 0,
                        "min": 0,
                        "max": 0,
                        "collapsed": "",
                        "button_label": "Ajouter un élément",
                        "rows_per_page": 20,
                        "sub_fields": [
                            {
                                "key": "field_68b84bf040c20",
                                "label": "Nom",
                                "name": "name",
                                "aria-label": "",
                                "type": "text",
                                "instructions": "",
                                "required": 0,
                                "conditional_logic": 0,
                                "wrapper": {
                                    "width": "",
                                    "class": "",
                                    "id": ""
                                },
                                "default_value": "",
                                "maxlength": "",
                                "allow_in_bindings": 0,
                                "placeholder": "",
                                "prepend": "",
                                "append": "",
                                "parent_repeater": "field_68b84bcc40c1f"
                            },
                            {
                                "key": "field_68b84c0640c21",
                                "label": "Niveau",
                                "name": "level",
                                "aria-label": "",
                                "type": "number",
                                "instructions": "",
                                "required": 0,
                                "conditional_logic": 0,
                                "wrapper": {
                                    "width": "",
                                    "class": "",
                                    "id": ""
                                },
                                "default_value": "",
                                "min": 0,
                                "max": 100,
                                "allow_in_bindings": 0,
                                "placeholder": "",
                                "step": "",
                                "prepend": "",
                                "append": "",
                                "parent_repeater": "field_68b84bcc40c1f"
                            },
                            {
                                "key": "field_68b84c2e40c22",
                                "label": "Icône",
                                "name": "icon",
                                "aria-label": "",
                                "type": "text",
                                "instructions": "",
                                "required": 0,
                                "conditional_logic": 0,
                                "wrapper": {
                                    "width": "",
                                    "class": "",
                                    "id": ""
                                },
                                "default_value": "fas fa-code",
                                "maxlength": "",
                                "allow_in_bindings": 0,
                                "placeholder": "",
                                "prepend": "",
                                "append": "",
                                "parent_repeater": "field_68b84bcc40c1f"
                            }
                        ],
                        "parent_repeater": "field_68b847e9083ff"
                    },
                    {
                        "key": "field_68b84c8140c23",
                        "label": "Outils & Technologies",
                        "name": "tools",
                        "aria-label": "",
                        "type": "repeater",
                        "instructions": "",
                        "required": 0,
                        "conditional_logic": 0,
                        "wrapper": {
                            "width": "",
                            "class": "",
                            "id": ""
                        },
                        "layout": "table",
                        "pagination": 0,
                        "min": 0,
                        "max": 0,
                        "collapsed": "",
                        "button_label": "Ajouter un élément",
                        "rows_per_page": 20,
                        "sub_fields": [
                            {
                                "key": "field_68b84ca540c24",
                                "label": "Nom",
                                "name": "name",
                                "aria-label": "",
                                "type": "text",
                                "instructions": "",
                                "required": 0,
                                "conditional_logic": 0,
                                "wrapper": {
                                    "width": "",
                                    "class": "",
                                    "id": ""
                                },
                                "default_value": "",
                                "maxlength": "",
                                "allow_in_bindings": 0,
                                "placeholder": "",
                                "prepend": "",
                                "append": "",
                                "parent_repeater": "field_68b84c8140c23"
                            },
                            {
                                "key": "field_68b84cb140c25",
                                "label": "Logo",
                                "name": "logo",
                                "aria-label": "",
                                "type": "image",
                                "instructions": "",
                                "required": 0,
                                "conditional_logic": 0,
                                "wrapper": {
                                    "width": "",
                                    "class": "",
                                    "id": ""
                                },
                                "return_format": "url",
                                "library": "all",
                                "min_width": "",
                                "min_height": "",
                                "min_size": "",
                                "max_width": "",
                                "max_height": "",
                                "max_size": "",
                                "mime_types": "",
                                "allow_in_bindings": 0,
                                "preview_size": "medium",
                                "parent_repeater": "field_68b84c8140c23"
                            }
                        ],
                        "parent_repeater": "field_68b847e9083ff"
                    }
                ]
            }
        ],
        "location": [
            [
                {
                    "param": "options_page",
                    "operator": "==",
                    "value": "acf-options-competences"
                }
            ]
        ],
        "menu_order": 0,
        "position": "normal",
        "style": "default",
        "label_placement": "top",
        "instruction_placement": "label",
        "hide_on_screen": "",
        "active": true,
        "description": "",
        "show_in_rest": 0
    },
    {
        "key": "group_68b84d2380913",
        "title": "Expérience professionnelle",
        "fields": [
            {
                "key": "field_68b84d2429698",
                "label": "Expériences",
                "name": "experiences",
                "aria-label": "",
                "type": "repeater",
                "instructions": "",
                "required": 0,
                "conditional_logic": 0,
                "wrapper": {
                    "width": "",
                    "class": "",
                    "id": ""
                },
                "layout": "table",
                "pagination": 0,
                "min": 0,
                "max": 0,
                "collapsed": "",
                "button_label": "Ajouter un élément",
                "rows_per_page": 20,
                "sub_fields": [
                    {
                        "key": "field_68b84d9a29699",
                        "label": "Titre du poste",
                        "name": "job_title",
                        "aria-label": "",
                        "type": "text",
                        "instructions": "",
                        "required": 0,
                        "conditional_logic": 0,
                        "wrapper": {
                            "width": "",
                            "class": "",
                            "id": ""
                        },
                        "default_value": "",
                        "maxlength": "",
                        "allow_in_bindings": 0,
                        "placeholder": "",
                        "prepend": "",
                        "append": "",
                        "parent_repeater": "field_68b84d2429698"
                    },
                    {
                        "key": "field_68b84db02969a",
                        "label": "Nom de lentreprise",
                        "name": "company_name",
                        "aria-label": "",
                        "type": "text",
                        "instructions": "",
                        "required": 0,
                        "conditional_logic": 0,
                        "wrapper": {
                            "width": "",
                            "class": "",
                            "id": ""
                        },
                        "default_value": "",
                        "maxlength": "",
                        "allow_in_bindings": 0,
                        "placeholder": "",
                        "prepend": "",
                        "append": "",
                        "parent_repeater": "field_68b84d2429698"
                    },
                    {
                        "key": "field_68b84ddb2969b",
                        "label": "Logo de l'entreprise",
                        "name": "company_logo",
                        "aria-label": "",
                        "type": "image",
                        "instructions": "",
                        "required": 0,
                        "conditional_logic": 0,
                        "wrapper": {
                            "width": "",
                            "class": "",
                            "id": ""
                        },
                        "return_format": "url",
                        "library": "all",
                        "min_width": "",
                        "min_height": "",
                        "min_size": "",
                        "max_width": "",
                        "max_height": "",
                        "max_size": "",
                        "mime_types": "",
                        "allow_in_bindings": 0,
                        "preview_size": "medium",
                        "parent_repeater": "field_68b84d2429698"
                    },
                    {
                        "key": "field_68b84dfa2969c",
                        "label": "Date de début",
                        "name": "start_date",
                        "aria-label": "",
                        "type": "date_picker",
                        "instructions": "",
                        "required": 0,
                        "conditional_logic": 0,
                        "wrapper": {
                            "width": "",
                            "class": "",
                            "id": ""
                        },
                        "display_format": "d\/m\/Y",
                        "return_format": "d\/m\/Y",
                        "first_day": 1,
                        "default_to_current_date": 0,
                        "allow_in_bindings": 0,
                        "parent_repeater": "field_68b84d2429698"
                    },
                    {
                        "key": "field_68be9bdf6d4c6",
                        "label": "End date",
                        "name": "end_date",
                        "aria-label": "",
                        "type": "date_picker",
                        "instructions": "",
                        "required": 0,
                        "conditional_logic": 0,
                        "wrapper": {
                            "width": "",
                            "class": "",
                            "id": ""
                        },
                        "display_format": "d\/m\/Y",
                        "return_format": "d\/m\/Y",
                        "first_day": 1,
                        "default_to_current_date": 0,
                        "allow_in_bindings": 0,
                        "parent_repeater": "field_68b84d2429698"
                    }
                ]
            }
        ],
        "location": [
            [
                {
                    "param": "options_page",
                    "operator": "==",
                    "value": "acf-options-experiences"
                }
            ]
        ],
        "menu_order": 0,
        "position": "normal",
        "style": "default",
        "label_placement": "top",
        "instruction_placement": "label",
        "hide_on_screen": "",
        "active": true,
        "description": "",
        "show_in_rest": 0
    },
    {
        "key": "group_68b8118c0418a",
        "title": "Informations personnelles",
        "fields": [
            {
                "key": "field_68b8118ca4b6e",
                "label": "Photo de profil",
                "name": "profile_photo",
                "aria-label": "",
                "type": "image",
                "instructions": "",
                "required": 0,
                "conditional_logic": 0,
                "wrapper": {
                    "width": "",
                    "class": "",
                    "id": ""
                },
                "return_format": "url",
                "library": "all",
                "min_width": "",
                "min_height": "",
                "min_size": "",
                "max_width": "",
                "max_height": "",
                "max_size": "",
                "mime_types": "",
                "allow_in_bindings": 0,
                "preview_size": "medium"
            },
            {
                "key": "field_68b81202a4b6f",
                "label": "Texte de présentation",
                "name": "about_text",
                "aria-label": "",
                "type": "wysiwyg",
                "instructions": "",
                "required": 0,
                "conditional_logic": 0,
                "wrapper": {
                    "width": "",
                    "class": "",
                    "id": ""
                },
                "default_value": "",
                "allow_in_bindings": 0,
                "tabs": "all",
                "toolbar": "full",
                "media_upload": 1,
                "delay": 0
            },
            {
                "key": "field_68b8121da4b70",
                "label": "Age",
                "name": "age",
                "aria-label": "",
                "type": "number",
                "instructions": "",
                "required": 0,
                "conditional_logic": 0,
                "wrapper": {
                    "width": "",
                    "class": "",
                    "id": ""
                },
                "default_value": "",
                "min": "",
                "max": "",
                "allow_in_bindings": 0,
                "placeholder": "",
                "step": "",
                "prepend": "",
                "append": ""
            },
            {
                "key": "field_68b8122aa4b71",
                "label": "Localisation",
                "name": "location",
                "aria-label": "",
                "type": "text",
                "instructions": "",
                "required": 0,
                "conditional_logic": 0,
                "wrapper": {
                    "width": "",
                    "class": "",
                    "id": ""
                },
                "default_value": "",
                "maxlength": "",
                "allow_in_bindings": 0,
                "placeholder": "",
                "prepend": "",
                "append": ""
            },
            {
                "key": "field_68b8123aa4b72",
                "label": "Email",
                "name": "email",
                "aria-label": "",
                "type": "email",
                "instructions": "",
                "required": 0,
                "conditional_logic": 0,
                "wrapper": {
                    "width": "",
                    "class": "",
                    "id": ""
                },
                "default_value": "",
                "allow_in_bindings": 0,
                "placeholder": "",
                "prepend": "",
                "append": ""
            },
            {
                "key": "field_68b81247a4b73",
                "label": "Téléphone",
                "name": "phone",
                "aria-label": "",
                "type": "text",
                "instructions": "",
                "required": 0,
                "conditional_logic": 0,
                "wrapper": {
                    "width": "",
                    "class": "",
                    "id": ""
                },
                "default_value": "",
                "maxlength": "",
                "allow_in_bindings": 0,
                "placeholder": "",
                "prepend": "",
                "append": ""
            },
            {
                "key": "field_68b81264a4b74",
                "label": "Facebook",
                "name": "social-facebook",
                "aria-label": "",
                "type": "group",
                "instructions": "",
                "required": 0,
                "conditional_logic": 0,
                "wrapper": {
                    "width": "",
                    "class": "",
                    "id": ""
                },
                "layout": "block",
                "sub_fields": [
                    {
                        "key": "field_68b812a4a4b75",
                        "label": "Plateforme",
                        "name": "plateform",
                        "aria-label": "",
                        "type": "text",
                        "instructions": "",
                        "required": 0,
                        "conditional_logic": 0,
                        "wrapper": {
                            "width": "",
                            "class": "",
                            "id": ""
                        },
                        "default_value": "LinkedIn",
                        "maxlength": "",
                        "allow_in_bindings": 0,
                        "placeholder": "",
                        "prepend": "",
                        "append": ""
                    },
                    {
                        "key": "field_68b812d6a4b76",
                        "label": "URL",
                        "name": "url",
                        "aria-label": "",
                        "type": "url",
                        "instructions": "",
                        "required": 0,
                        "conditional_logic": 0,
                        "wrapper": {
                            "width": "",
                            "class": "",
                            "id": ""
                        },
                        "default_value": "",
                        "allow_in_bindings": 0,
                        "placeholder": ""
                    },
                    {
                        "key": "field_68b812e3a4b77",
                        "label": "Icone",
                        "name": "icon",
                        "aria-label": "",
                        "type": "text",
                        "instructions": "",
                        "required": 0,
                        "conditional_logic": 0,
                        "wrapper": {
                            "width": "",
                            "class": "",
                            "id": ""
                        },
                        "default_value": "fas fa-linkedin",
                        "maxlength": "",
                        "allow_in_bindings": 0,
                        "placeholder": "",
                        "prepend": "",
                        "append": ""
                    }
                ]
            },
            {
                "key": "field_68b8466c11a9b",
                "label": "Linkedin",
                "name": "social-linkedin",
                "aria-label": "",
                "type": "group",
                "instructions": "",
                "required": 0,
                "conditional_logic": 0,
                "wrapper": {
                    "width": "",
                    "class": "",
                    "id": ""
                },
                "layout": "block",
                "sub_fields": [
                    {
                        "key": "field_68b846c411a9c",
                        "label": "Plateform",
                        "name": "plateform",
                        "aria-label": "",
                        "type": "text",
                        "instructions": "",
                        "required": 0,
                        "conditional_logic": 0,
                        "wrapper": {
                            "width": "",
                            "class": "",
                            "id": ""
                        },
                        "default_value": "Linkedin",
                        "maxlength": "",
                        "allow_in_bindings": 0,
                        "placeholder": "",
                        "prepend": "",
                        "append": ""
                    },
                    {
                        "key": "field_68b8475b11a9d",
                        "label": "URL",
                        "name": "url",
                        "aria-label": "",
                        "type": "url",
                        "instructions": "",
                        "required": 0,
                        "conditional_logic": 0,
                        "wrapper": {
                            "width": "",
                            "class": "",
                            "id": ""
                        },
                        "default_value": "",
                        "allow_in_bindings": 0,
                        "placeholder": ""
                    },
                    {
                        "key": "field_68b8477311a9e",
                        "label": "Icône",
                        "name": "icon",
                        "aria-label": "",
                        "type": "text",
                        "instructions": "",
                        "required": 0,
                        "conditional_logic": 0,
                        "wrapper": {
                            "width": "",
                            "class": "",
                            "id": ""
                        },
                        "default_value": "fas fa-linkedin",
                        "maxlength": "",
                        "allow_in_bindings": 0,
                        "placeholder": "",
                        "prepend": "",
                        "append": ""
                    }
                ]
            }
        ],
        "location": [
            [
                {
                    "param": "options_page",
                    "operator": "==",
                    "value": "acf-options-infos-personnelles"
                }
            ]
        ],
        "menu_order": 0,
        "position": "normal",
        "style": "default",
        "label_placement": "top",
        "instruction_placement": "label",
        "hide_on_screen": "",
        "active": true,
        "description": "",
        "show_in_rest": 0
    }
]
